video_to_transcript/__init__.py
video_to_transcript/package.py
video_to_transcript-0.0.7.dist-info/METADATA
video_to_transcript-0.0.7.dist-info/WHEEL
video_to_transcript-0.0.7.dist-info/top_level.txt
video_to_transcript-0.0.7.dist-info/RECORD
