Metadata-Version: 2.1
Name: video-to-transcript
Version: 0.0.7
Summary: Video speech Extracter
Home-page: UNKNOWN
Author: Asher Mathews Shaji
Author-email: msasher123@gmail.com
License: UNKNOWN
Keywords: python,video,stream,video stream,camera stream,sockets,transcript
Platform: UNKNOWN
Classifier: Development Status :: 1 - Planning
Classifier: Intended Audience :: Developers
Classifier: Programming Language :: Python :: 3
Classifier: Operating System :: Unix
Classifier: Operating System :: MacOS :: MacOS X
Classifier: Operating System :: Microsoft :: Windows
Requires-Dist: moviepy
Requires-Dist: SpeechRecognition
